{
    "item.array":"Grupo de textos",
    "item.bigtext":"Texto grande",
    "item.check":"Checagem",
    "item.enum":"Seleção",
    "item.file":"Arquivo",
    "item.text":"Texto",
    "item.check.checked":"Sim",
    "item.check.unchecked":"Não",
    "item.action.add.prompt":"Insira a descrição do novo item",
    "item.action.add.array":"+ Grupo de textos",
    "item.action.add.bigtext":"+ Texto grande",
    "item.action.add.check":"+ Checagem",
    "item.action.add.enum":"+ Seleção",
    "item.action.add.file":"+ Arquivo",
    "item.action.add.text":"+ Texto",
    "item.action.save":"Salvar",
    "item.action.cancel":"Cancelar",
    "item.array.spec.items":"Ítens",
    "item.array.spec.items.help":"(Um por linha)",
    "item.bigtext.spec.minwords":"Mínimo de palavras",
    "item.bigtext.spec.maxwords":"Máximo de palavras",
    "item.enum.spec.items":"Ítens",
    "item.enum.spec.items.help":"(Um por linha)",
    "item.file.spec.maxsize":"Tamanho máximo (MB)",
    "item.file.spec.filetypes":"Tipos de arquivo permitidos",
    "item.description":"Descrição",
    "item.unrestrict":"Visão irrestrita",
    "item.mandatory":"Obrigatório",
    "control.action.change":"Alterar",
    "control.enum.null":"&gt;&gt; Selecione",
    "control.restriction.start":" (",
    "control.restriction.end":")",
    "control.restriction.separator":", ",
    "control.restriction.mandatory":"Obrigatório",
    "control.restriction.minwords":"Min. palavras: ",
    "control.restriction.maxwords":"Máx. palavras:",
    "control.restriction.filetypes":"Tipos de arquivos: ",
    "control.restriction.filetypes.all":"todos ",
    "control.restriction.maxsize":"Tamanho máximo: ",
    "control.restriction.maxsize.megabytes":" MB",
    "structure.table.confirm.delete.1":"Tem certeza que deseja apagar o item na posição ",
    "structure.table.confirm.delete.2":"? ",
    "structure.table.header.position":"Posição",
    "structure.table.header.type":"Tipo",
    "structure.table.header.description":"Descrição",
    "structure.table.header.unrestrict":"V. Irrestrita",
    "structure.table.header.mandatory":"Obrigatório",
    "structure.table.header.options":"Opções"
}